pink/__init__.py
pink/configuration.py
pink/exceptions.py
pink/solve_ik.py
pink/utils.py
pink/visualization.py
pink/barriers/__init__.py
pink/barriers/barrier.py
pink/barriers/body_spherical_barrier.py
pink/barriers/position_barrier.py
pink/barriers/self_collision_barrier.py
pink/limits/__init__.py
pink/limits/acceleration_limit.py
pink/limits/configuration_limit.py
pink/limits/floating_base_velocity_limit.py
pink/limits/limit.py
pink/limits/velocity_limit.py
pink/tasks/__init__.py
pink/tasks/com_task.py
pink/tasks/damping_task.py
pink/tasks/frame_task.py
pink/tasks/joint_coupling_task.py
pink/tasks/joint_velocity_task.py
pink/tasks/linear_holonomic_task.py
pink/tasks/low_acceleration_task.py
pink/tasks/omniwheel_task.py
pink/tasks/posture_task.py
pink/tasks/relative_frame_task.py
pink/tasks/rolling_task.py
pink/tasks/task.py
pin_pink-4.0.0.dist-info/licenses/LICENSE
pin_pink-4.0.0.dist-info/WHEEL
pin_pink-4.0.0.dist-info/METADATA
pin_pink-4.0.0.dist-info/RECORD
