Metadata-Version: 2.4
Name: pin-pink
Version: 4.0.0
Summary: Inverse kinematics for articulated robot models, based on Pinocchio.
Keywords: inverse,kinematics,pinocchio
Author-email: Stéphane Caron <stephane.caron@normalesup.org>
Maintainer-email: Stéphane Caron <stephane.caron@normalesup.org>
Requires-Python: >=3.9
Classifier: Development Status :: 5 - Production/Stable
Classifier: Framework :: Robot Framework :: Library
Classifier: Intended Audience :: Developers
Classifier: Intended Audience :: Science/Research
Classifier: License :: OSI Approved :: Apache Software License
Classifier: Programming Language :: Python :: 3.9
Classifier: Programming Language :: Python :: 3.10
Classifier: Programming Language :: Python :: 3.11
Classifier: Programming Language :: Python :: 3.12
Classifier: Topic :: Scientific/Engineering
License-File: LICENSE
Requires-Dist: loop-rate-limiters >=0.1.0
Requires-Dist: numpy >=1.19.0
Requires-Dist: pin >=2.6.3
Requires-Dist: qpsolvers >=4.3.1
Project-URL: Changelog, https://github.com/stephane-caron/pink/blob/main/CHANGELOG.md
Project-URL: Documentation, https://stephane-caron.github.io/pink/
Project-URL: Homepage, https://stephane-caron.github.io/pink/
Project-URL: Source, https://github.com/stephane-caron/pink
Project-URL: Tracker, https://github.com/stephane-caron/pink/issues
